{"title":"Kaboom!","subtitle_A":"photo galleries","subtitle_B":"","siteLink":"<a href='https://awsum.ninja'>Awsum Ninja</a>","custom_nav":{"showGalleryHome":true,"homeRedirect":"demo-gallery","beforeMainList":{"category":"","links":[{"title":"Back to Main Site","subtitle_A":"http://example.com","url":"../"}]},"afterMainList":{"category":"Other Links","links":[{"title":"Related Site","subtitle_A":"more photos!","url":"https://example.com"},{"title":"Another Link","subtitle_A":"examples are great!","url":"https://example2.com"}]}},"notes":"Put a 'site-config.json' file in your /kaboom/ root directory with real values.","images":[],"svgSequences":{},"GALLERY_IS_HOME_PAGE":true,"lastUpdate":1615751273596,"section":"11-plus","imageCount":4,"latestUpdate":1615751273627,"controlPanelOpen":true,"allowDownloads":true,"navCategories":[]}